{"train_no": "5217", "has_breastfeeding_rooms": false, "carries_packages": false, "has_dining_rooms": false, "is_accessible": false, "has_bike_stands": false, "train_class": "110D", "stops": [{"station": "1715", "departs_at": "14:12", "arrives_at": "14:10"}, {"station": "1823", "departs_at": "15:21", "arrives_at": "15:19"}, {"station": "1820", "departs_at": "15:36", "arrives_at": "15:30"}, {"station": "1007", "departs_at": "17:04", "arrives_at": "17:03"}, {"station": "1008", "departs_at": "17:15", "arrives_at": "17:11"}, {"station": "1011", "departs_at": "17:26", "arrives_at": "17:24"}, {"station": "1012", "departs_at": "17:37", "arrives_at": "17:32"}]}